parquet_to_root/__init__.py
parquet_to_root/__main__.py
parquet_to_root/parquet_to_root_pyroot.py
tests/__init__.py
tests/test_run.py
parquet_to_root-0.3.0.dist-info/LICENSE
parquet_to_root-0.3.0.dist-info/METADATA
parquet_to_root-0.3.0.dist-info/WHEEL
parquet_to_root-0.3.0.dist-info/top_level.txt
parquet_to_root-0.3.0.dist-info/RECORD
