Metadata-Version: 2.1
Name: parquet-to-root
Version: 0.3.0
Summary: Parquet-to-ROOT translator
Home-page: https://github.com/ponyisi/parquet_to_root
Author: Peter Onyisi
Author-email: ponyisi@utexas.edu
License: UNKNOWN
Platform: UNKNOWN
Classifier: Programming Language :: Python :: 3
Classifier: License :: OSI Approved :: Apache Software License
Classifier: Operating System :: OS Independent
Requires-Python: >=3.6
Requires-Dist: pyarrow (>=2)
